Metadata-Version: 2.1
Name: data2vec
Version: 0.0.3
Summary: data2Vec是一个Python工具，用于数据向量表征。
Home-page: https://github.com/xuehangcang/data2vec
Author: Xuehang Cang
Author-email: xuehangcang@outlook.com
License: MIT License
Keywords: Vector Pytorch Vector Database
Platform: any
License-File: LICENSE
